{"indexes":[{"v":{"$numberInt":"2"},"key":{"_id":{"$numberInt":"1"}},"name":"_id_"},{"v":{"$numberInt":"2"},"key":{"mobile":{"$numberInt":"1"}},"name":"mobile_1","background":true,"unique":true},{"v":{"$numberInt":"2"},"key":{"qualifications.subQualification":{"$numberDouble":"-1.0"}},"name":"qualifications.subQualification_-1"},{"v":{"$numberInt":"2"},"key":{"location":"2dsphere"},"name":"location_2dsphere","2dsphereIndexVersion":{"$numberInt":"3"}},{"v":{"$numberInt":"2"},"key":{"isDeleted":{"$numberDouble":"-1.0"}},"name":"isDeleted_-1"},{"v":{"$numberInt":"2"},"key":{"status":{"$numberDouble":"-1.0"}},"name":"status_-1"},{"v":{"$numberInt":"2"},"key":{"_fts":"text","_ftsx":{"$numberInt":"1"}},"name":"highestQualification_text","weights":{"highestQualification":{"$numberInt":"1"}},"default_language":"english","language_override":"language","textIndexVersion":{"$numberInt":"3"}}],"uuid":"aecd3109544440afb2d3d772fed666bb","collectionName":"candidates","type":"collection"}